<mxfile host="app.diagrams.net" agent="Mozilla/5.0 (Windows NT 10.0; Win64; x64) AppleWebKit/537.36 (KHTML, like Gecko) Chrome/140.0.0.0 Safari/537.36" version="28.2.4">
  <diagram name="Restaurant POS Class Diagram" id="class-diagram">
    <mxGraphModel dx="2180" dy="1078" grid="1" gridSize="10" guides="1" tooltips="1" connect="1" arrows="1" fold="1" page="1" pageScale="1" pageWidth="1400" pageHeight="900" math="0" shadow="0">
      <root>
        <mxCell id="0" />
        <mxCell id="1" parent="0" />
        <mxCell id="user-class" value="" style="swimlane;fontStyle=1;align=center;verticalAlign=top;childLayout=stackLayout;horizontal=1;startSize=26;horizontalStack=0;resizeParent=1;resizeParentMax=0;resizeLast=0;collapsible=1;marginBottom=0;labelBackgroundColor=none;" parent="1" vertex="1">
          <mxGeometry x="50" y="50" width="200" height="210" as="geometry" />
        </mxCell>
        <mxCell id="user-title" value="User" style="text;strokeColor=none;fillColor=none;align=center;verticalAlign=top;spacingLeft=4;spacingRight=4;overflow=hidden;rotatable=0;points=[[0,0.5],[1,0.5]];portConstraint=eastwest;fontStyle=1;fontSize=16;labelBackgroundColor=none;" parent="user-class" vertex="1">
          <mxGeometry y="26" width="200" height="26" as="geometry" />
        </mxCell>
        <mxCell id="user-line" value="" style="line;strokeWidth=1;fillColor=none;align=left;verticalAlign=middle;spacingTop=-1;spacingLeft=3;spacingRight=3;rotatable=0;labelPosition=right;points=[];portConstraint=eastwest;labelBackgroundColor=none;" parent="user-class" vertex="1">
          <mxGeometry y="52" width="200" height="8" as="geometry" />
        </mxCell>
        <mxCell id="user-attrs" value="- id: int&#xa;- name: string&#xa;- email: string&#xa;- password: string&#xa;- role: string&#xa;- status: string" style="text;strokeColor=none;fillColor=none;align=left;verticalAlign=top;spacingLeft=4;spacingRight=4;overflow=hidden;rotatable=0;points=[[0,0.5],[1,0.5]];portConstraint=eastwest;labelBackgroundColor=none;" parent="user-class" vertex="1">
          <mxGeometry y="60" width="200" height="90" as="geometry" />
        </mxCell>
        <mxCell id="user-line2" value="" style="line;strokeWidth=1;fillColor=none;align=left;verticalAlign=middle;spacingTop=-1;spacingLeft=3;spacingRight=3;rotatable=0;labelPosition=right;points=[];portConstraint=eastwest;labelBackgroundColor=none;" parent="user-class" vertex="1">
          <mxGeometry y="150" width="200" height="8" as="geometry" />
        </mxCell>
        <mxCell id="user-methods" value="+ login(): boolean&#xa;+ logout(): void&#xa;+ hasRole(role): boolean" style="text;strokeColor=none;fillColor=none;align=left;verticalAlign=top;spacingLeft=4;spacingRight=4;overflow=hidden;rotatable=0;points=[[0,0.5],[1,0.5]];portConstraint=eastwest;labelBackgroundColor=none;" parent="user-class" vertex="1">
          <mxGeometry y="158" width="200" height="52" as="geometry" />
        </mxCell>
        <mxCell id="menuitem-class" value="" style="swimlane;fontStyle=1;align=center;verticalAlign=top;childLayout=stackLayout;horizontal=1;startSize=26;horizontalStack=0;resizeParent=1;resizeParentMax=0;resizeLast=0;collapsible=1;marginBottom=0;labelBackgroundColor=none;" parent="1" vertex="1">
          <mxGeometry x="950" y="290" width="200" height="220" as="geometry" />
        </mxCell>
        <mxCell id="menuitem-title" value="MenuItem" style="text;strokeColor=none;fillColor=none;align=center;verticalAlign=top;spacingLeft=4;spacingRight=4;overflow=hidden;rotatable=0;points=[[0,0.5],[1,0.5]];portConstraint=eastwest;fontStyle=1;fontSize=16;labelBackgroundColor=none;" parent="menuitem-class" vertex="1">
          <mxGeometry y="26" width="200" height="26" as="geometry" />
        </mxCell>
        <mxCell id="menuitem-line" value="" style="line;strokeWidth=1;fillColor=none;align=left;verticalAlign=middle;spacingTop=-1;spacingLeft=3;spacingRight=3;rotatable=0;labelPosition=right;points=[];portConstraint=eastwest;labelBackgroundColor=none;" parent="menuitem-class" vertex="1">
          <mxGeometry y="52" width="200" height="8" as="geometry" />
        </mxCell>
        <mxCell id="menuitem-attrs" value="- id: int&#xa;- name: string&#xa;- description: string&#xa;- price: decimal&#xa;- category: string&#xa;- available: boolean&#xa;- preparationTime: int" style="text;strokeColor=none;fillColor=none;align=left;verticalAlign=top;spacingLeft=4;spacingRight=4;overflow=hidden;rotatable=0;points=[[0,0.5],[1,0.5]];portConstraint=eastwest;labelBackgroundColor=none;" parent="menuitem-class" vertex="1">
          <mxGeometry y="60" width="200" height="110" as="geometry" />
        </mxCell>
        <mxCell id="menuitem-line2" value="" style="line;strokeWidth=1;fillColor=none;align=left;verticalAlign=middle;spacingTop=-1;spacingLeft=3;spacingRight=3;rotatable=0;labelPosition=right;points=[];portConstraint=eastwest;labelBackgroundColor=none;" parent="menuitem-class" vertex="1">
          <mxGeometry y="170" width="200" height="8" as="geometry" />
        </mxCell>
        <mxCell id="menuitem-methods" value="+ isAvailable(): boolean&#xa;+ updatePrice(price): void&#xa;+ setAvailability(status): void" style="text;strokeColor=none;fillColor=none;align=left;verticalAlign=top;spacingLeft=4;spacingRight=4;overflow=hidden;rotatable=0;points=[[0,0.5],[1,0.5]];portConstraint=eastwest;labelBackgroundColor=none;" parent="menuitem-class" vertex="1">
          <mxGeometry y="178" width="200" height="42" as="geometry" />
        </mxCell>
        <mxCell id="order-class" value="" style="swimlane;fontStyle=1;align=center;verticalAlign=top;childLayout=stackLayout;horizontal=1;startSize=26;horizontalStack=0;resizeParent=1;resizeParentMax=0;resizeLast=0;collapsible=1;marginBottom=0;labelBackgroundColor=none;" parent="1" vertex="1">
          <mxGeometry x="490" y="30" width="200" height="260" as="geometry" />
        </mxCell>
        <mxCell id="order-title" value="Order" style="text;strokeColor=none;fillColor=none;align=center;verticalAlign=top;spacingLeft=4;spacingRight=4;overflow=hidden;rotatable=0;points=[[0,0.5],[1,0.5]];portConstraint=eastwest;fontStyle=1;fontSize=16;labelBackgroundColor=none;" parent="order-class" vertex="1">
          <mxGeometry y="26" width="200" height="26" as="geometry" />
        </mxCell>
        <mxCell id="order-line" value="" style="line;strokeWidth=1;fillColor=none;align=left;verticalAlign=middle;spacingTop=-1;spacingLeft=3;spacingRight=3;rotatable=0;labelPosition=right;points=[];portConstraint=eastwest;labelBackgroundColor=none;" parent="order-class" vertex="1">
          <mxGeometry y="52" width="200" height="8" as="geometry" />
        </mxCell>
        <mxCell id="order-attrs" value="- id: int&#xa;- orderNumber: string&#xa;- customerName: string&#xa;- tableNumber: string&#xa;- status: string&#xa;- totalAmount: decimal&#xa;- waiterId: int&#xa;- createdAt: datetime" style="text;strokeColor=none;fillColor=none;align=left;verticalAlign=top;spacingLeft=4;spacingRight=4;overflow=hidden;rotatable=0;points=[[0,0.5],[1,0.5]];portConstraint=eastwest;labelBackgroundColor=none;" parent="order-class" vertex="1">
          <mxGeometry y="60" width="200" height="120" as="geometry" />
        </mxCell>
        <mxCell id="order-line2" value="" style="line;strokeWidth=1;fillColor=none;align=left;verticalAlign=middle;spacingTop=-1;spacingLeft=3;spacingRight=3;rotatable=0;labelPosition=right;points=[];portConstraint=eastwest;labelBackgroundColor=none;" parent="order-class" vertex="1">
          <mxGeometry y="180" width="200" height="8" as="geometry" />
        </mxCell>
        <mxCell id="order-methods" value="+ calculateTotal(): decimal&#xa;+ addItem(item): void&#xa;+ updateStatus(status): void&#xa;+ generateOrderNumber(): string" style="text;strokeColor=none;fillColor=none;align=left;verticalAlign=top;spacingLeft=4;spacingRight=4;overflow=hidden;rotatable=0;points=[[0,0.5],[1,0.5]];portConstraint=eastwest;labelBackgroundColor=none;" parent="order-class" vertex="1">
          <mxGeometry y="188" width="200" height="72" as="geometry" />
        </mxCell>
        <mxCell id="orderitem-class" value="" style="swimlane;fontStyle=1;align=center;verticalAlign=top;childLayout=stackLayout;horizontal=1;startSize=26;horizontalStack=0;resizeParent=1;resizeParentMax=0;resizeLast=0;collapsible=1;marginBottom=0;labelBackgroundColor=none;" parent="1" vertex="1">
          <mxGeometry x="800" y="50" width="200" height="180" as="geometry" />
        </mxCell>
        <mxCell id="orderitem-title" value="OrderItem" style="text;strokeColor=none;fillColor=none;align=center;verticalAlign=top;spacingLeft=4;spacingRight=4;overflow=hidden;rotatable=0;points=[[0,0.5],[1,0.5]];portConstraint=eastwest;fontStyle=1;fontSize=16;labelBackgroundColor=none;" parent="orderitem-class" vertex="1">
          <mxGeometry y="26" width="200" height="26" as="geometry" />
        </mxCell>
        <mxCell id="orderitem-line" value="" style="line;strokeWidth=1;fillColor=none;align=left;verticalAlign=middle;spacingTop=-1;spacingLeft=3;spacingRight=3;rotatable=0;labelPosition=right;points=[];portConstraint=eastwest;labelBackgroundColor=none;" parent="orderitem-class" vertex="1">
          <mxGeometry y="52" width="200" height="8" as="geometry" />
        </mxCell>
        <mxCell id="orderitem-attrs" value="- id: int&#xa;- orderId: int&#xa;- menuItemId: int&#xa;- quantity: int&#xa;- itemPrice: decimal&#xa;- subtotal: decimal" style="text;strokeColor=none;fillColor=none;align=left;verticalAlign=top;spacingLeft=4;spacingRight=4;overflow=hidden;rotatable=0;points=[[0,0.5],[1,0.5]];portConstraint=eastwest;labelBackgroundColor=none;" parent="orderitem-class" vertex="1">
          <mxGeometry y="60" width="200" height="90" as="geometry" />
        </mxCell>
        <mxCell id="orderitem-line2" value="" style="line;strokeWidth=1;fillColor=none;align=left;verticalAlign=middle;spacingTop=-1;spacingLeft=3;spacingRight=3;rotatable=0;labelPosition=right;points=[];portConstraint=eastwest;labelBackgroundColor=none;" parent="orderitem-class" vertex="1">
          <mxGeometry y="150" width="200" height="8" as="geometry" />
        </mxCell>
        <mxCell id="orderitem-methods" value="+ calculateSubtotal(): decimal" style="text;strokeColor=none;fillColor=none;align=left;verticalAlign=top;spacingLeft=4;spacingRight=4;overflow=hidden;rotatable=0;points=[[0,0.5],[1,0.5]];portConstraint=eastwest;labelBackgroundColor=none;" parent="orderitem-class" vertex="1">
          <mxGeometry y="158" width="200" height="22" as="geometry" />
        </mxCell>
        <mxCell id="bill-class" value="" style="swimlane;fontStyle=1;align=center;verticalAlign=top;childLayout=stackLayout;horizontal=1;startSize=26;horizontalStack=0;resizeParent=1;resizeParentMax=0;resizeLast=0;collapsible=1;marginBottom=0;labelBackgroundColor=none;" parent="1" vertex="1">
          <mxGeometry x="490" y="480" width="200" height="240" as="geometry" />
        </mxCell>
        <mxCell id="bill-title" value="Bill" style="text;strokeColor=none;fillColor=none;align=center;verticalAlign=top;spacingLeft=4;spacingRight=4;overflow=hidden;rotatable=0;points=[[0,0.5],[1,0.5]];portConstraint=eastwest;fontStyle=1;fontSize=16;labelBackgroundColor=none;" parent="bill-class" vertex="1">
          <mxGeometry y="26" width="200" height="26" as="geometry" />
        </mxCell>
        <mxCell id="bill-line" value="" style="line;strokeWidth=1;fillColor=none;align=left;verticalAlign=middle;spacingTop=-1;spacingLeft=3;spacingRight=3;rotatable=0;labelPosition=right;points=[];portConstraint=eastwest;labelBackgroundColor=none;" parent="bill-class" vertex="1">
          <mxGeometry y="52" width="200" height="8" as="geometry" />
        </mxCell>
        <mxCell id="bill-attrs" value="- id: int&#xa;- billNumber: string&#xa;- orderId: int&#xa;- subtotal: decimal&#xa;- taxAmount: decimal&#xa;- totalAmount: decimal&#xa;- paymentStatus: string&#xa;- paymentMethod: string" style="text;strokeColor=none;fillColor=none;align=left;verticalAlign=top;spacingLeft=4;spacingRight=4;overflow=hidden;rotatable=0;points=[[0,0.5],[1,0.5]];portConstraint=eastwest;labelBackgroundColor=none;" parent="bill-class" vertex="1">
          <mxGeometry y="60" width="200" height="120" as="geometry" />
        </mxCell>
        <mxCell id="bill-line2" value="" style="line;strokeWidth=1;fillColor=none;align=left;verticalAlign=middle;spacingTop=-1;spacingLeft=3;spacingRight=3;rotatable=0;labelPosition=right;points=[];portConstraint=eastwest;labelBackgroundColor=none;" parent="bill-class" vertex="1">
          <mxGeometry y="180" width="200" height="8" as="geometry" />
        </mxCell>
        <mxCell id="bill-methods" value="+ calculateTotal(): decimal&#xa;+ markAsPaid(): void&#xa;+ generateBillNumber(): string" style="text;strokeColor=none;fillColor=none;align=left;verticalAlign=top;spacingLeft=4;spacingRight=4;overflow=hidden;rotatable=0;points=[[0,0.5],[1,0.5]];portConstraint=eastwest;labelBackgroundColor=none;" parent="bill-class" vertex="1">
          <mxGeometry y="188" width="200" height="52" as="geometry" />
        </mxCell>
        <mxCell id="inventory-class" value="" style="swimlane;fontStyle=1;align=center;verticalAlign=top;childLayout=stackLayout;horizontal=1;startSize=26;horizontalStack=0;resizeParent=1;resizeParentMax=0;resizeLast=0;collapsible=1;marginBottom=0;labelBackgroundColor=none;" parent="1" vertex="1">
          <mxGeometry x="780" y="600" width="200" height="230" as="geometry" />
        </mxCell>
        <mxCell id="inventory-title" value="Inventory" style="text;strokeColor=none;fillColor=none;align=center;verticalAlign=top;spacingLeft=4;spacingRight=4;overflow=hidden;rotatable=0;points=[[0,0.5],[1,0.5]];portConstraint=eastwest;fontStyle=1;fontSize=16;labelBackgroundColor=none;" parent="inventory-class" vertex="1">
          <mxGeometry y="26" width="200" height="26" as="geometry" />
        </mxCell>
        <mxCell id="inventory-line" value="" style="line;strokeWidth=1;fillColor=none;align=left;verticalAlign=middle;spacingTop=-1;spacingLeft=3;spacingRight=3;rotatable=0;labelPosition=right;points=[];portConstraint=eastwest;labelBackgroundColor=none;" parent="inventory-class" vertex="1">
          <mxGeometry y="52" width="200" height="8" as="geometry" />
        </mxCell>
        <mxCell id="inventory-attrs" value="- id: int&#xa;- name: string&#xa;- quantity: decimal&#xa;- unit: string&#xa;- threshold: decimal&#xa;- cost: decimal&#xa;- supplier: string&#xa;- expiryDate: date" style="text;strokeColor=none;fillColor=none;align=left;verticalAlign=top;spacingLeft=4;spacingRight=4;overflow=hidden;rotatable=0;points=[[0,0.5],[1,0.5]];portConstraint=eastwest;labelBackgroundColor=none;" parent="inventory-class" vertex="1">
          <mxGeometry y="60" width="200" height="120" as="geometry" />
        </mxCell>
        <mxCell id="inventory-line2" value="" style="line;strokeWidth=1;fillColor=none;align=left;verticalAlign=middle;spacingTop=-1;spacingLeft=3;spacingRight=3;rotatable=0;labelPosition=right;points=[];portConstraint=eastwest;labelBackgroundColor=none;" parent="inventory-class" vertex="1">
          <mxGeometry y="180" width="200" height="8" as="geometry" />
        </mxCell>
        <mxCell id="inventory-methods" value="+ getStockStatus(): string&#xa;+ adjustStock(amount): boolean" style="text;strokeColor=none;fillColor=none;align=left;verticalAlign=top;spacingLeft=4;spacingRight=4;overflow=hidden;rotatable=0;points=[[0,0.5],[1,0.5]];portConstraint=eastwest;labelBackgroundColor=none;" parent="inventory-class" vertex="1">
          <mxGeometry y="188" width="200" height="42" as="geometry" />
        </mxCell>
        <mxCell id="setting-class" value="" style="swimlane;fontStyle=1;align=center;verticalAlign=top;childLayout=stackLayout;horizontal=1;startSize=26;horizontalStack=0;resizeParent=1;resizeParentMax=0;resizeLast=0;collapsible=1;marginBottom=0;labelBackgroundColor=none;" parent="1" vertex="1">
          <mxGeometry x="260" y="660" width="200" height="200" as="geometry" />
        </mxCell>
        <mxCell id="setting-title" value="Setting" style="text;strokeColor=none;fillColor=none;align=center;verticalAlign=top;spacingLeft=4;spacingRight=4;overflow=hidden;rotatable=0;points=[[0,0.5],[1,0.5]];portConstraint=eastwest;fontStyle=1;fontSize=16;labelBackgroundColor=none;" parent="setting-class" vertex="1">
          <mxGeometry y="26" width="200" height="26" as="geometry" />
        </mxCell>
        <mxCell id="setting-line" value="" style="line;strokeWidth=1;fillColor=none;align=left;verticalAlign=middle;spacingTop=-1;spacingLeft=3;spacingRight=3;rotatable=0;labelPosition=right;points=[];portConstraint=eastwest;labelBackgroundColor=none;" parent="setting-class" vertex="1">
          <mxGeometry y="52" width="200" height="8" as="geometry" />
        </mxCell>
        <mxCell id="setting-attrs" value="- id: int&#xa;- key: string&#xa;- value: string&#xa;- type: string&#xa;- category: string&#xa;- isPublic: boolean" style="text;strokeColor=none;fillColor=none;align=left;verticalAlign=top;spacingLeft=4;spacingRight=4;overflow=hidden;rotatable=0;points=[[0,0.5],[1,0.5]];portConstraint=eastwest;labelBackgroundColor=none;" parent="setting-class" vertex="1">
          <mxGeometry y="60" width="200" height="90" as="geometry" />
        </mxCell>
        <mxCell id="setting-line2" value="" style="line;strokeWidth=1;fillColor=none;align=left;verticalAlign=middle;spacingTop=-1;spacingLeft=3;spacingRight=3;rotatable=0;labelPosition=right;points=[];portConstraint=eastwest;labelBackgroundColor=none;" parent="setting-class" vertex="1">
          <mxGeometry y="150" width="200" height="8" as="geometry" />
        </mxCell>
        <mxCell id="setting-methods" value="+ get(key): mixed&#xa;+ set(key, value): void" style="text;strokeColor=none;fillColor=none;align=left;verticalAlign=top;spacingLeft=4;spacingRight=4;overflow=hidden;rotatable=0;points=[[0,0.5],[1,0.5]];portConstraint=eastwest;labelBackgroundColor=none;" parent="setting-class" vertex="1">
          <mxGeometry y="158" width="200" height="42" as="geometry" />
        </mxCell>
        <mxCell id="report-class" value="" style="swimlane;fontStyle=1;align=center;verticalAlign=top;childLayout=stackLayout;horizontal=1;startSize=26;horizontalStack=0;resizeParent=1;resizeParentMax=0;resizeLast=0;collapsible=1;marginBottom=0;labelBackgroundColor=none;" parent="1" vertex="1">
          <mxGeometry x="50" y="440" width="200" height="200" as="geometry" />
        </mxCell>
        <mxCell id="report-title" value="Report" style="text;strokeColor=none;fillColor=none;align=center;verticalAlign=top;spacingLeft=4;spacingRight=4;overflow=hidden;rotatable=0;points=[[0,0.5],[1,0.5]];portConstraint=eastwest;fontStyle=1;fontSize=16;labelBackgroundColor=none;" parent="report-class" vertex="1">
          <mxGeometry y="26" width="200" height="26" as="geometry" />
        </mxCell>
        <mxCell id="report-line" value="" style="line;strokeWidth=1;fillColor=none;align=left;verticalAlign=middle;spacingTop=-1;spacingLeft=3;spacingRight=3;rotatable=0;labelPosition=right;points=[];portConstraint=eastwest;labelBackgroundColor=none;" parent="report-class" vertex="1">
          <mxGeometry y="52" width="200" height="8" as="geometry" />
        </mxCell>
        <mxCell id="report-attrs" value="- id: int&#xa;- reportName: string&#xa;- reportType: string&#xa;- data: json&#xa;- generatedBy: int&#xa;- generatedAt: datetime" style="text;strokeColor=none;fillColor=none;align=left;verticalAlign=top;spacingLeft=4;spacingRight=4;overflow=hidden;rotatable=0;points=[[0,0.5],[1,0.5]];portConstraint=eastwest;labelBackgroundColor=none;" parent="report-class" vertex="1">
          <mxGeometry y="60" width="200" height="90" as="geometry" />
        </mxCell>
        <mxCell id="report-line2" value="" style="line;strokeWidth=1;fillColor=none;align=left;verticalAlign=middle;spacingTop=-1;spacingLeft=3;spacingRight=3;rotatable=0;labelPosition=right;points=[];portConstraint=eastwest;labelBackgroundColor=none;" parent="report-class" vertex="1">
          <mxGeometry y="150" width="200" height="8" as="geometry" />
        </mxCell>
        <mxCell id="report-methods" value="+ generateReport(): void&#xa;+ exportData(): string" style="text;strokeColor=none;fillColor=none;align=left;verticalAlign=top;spacingLeft=4;spacingRight=4;overflow=hidden;rotatable=0;points=[[0,0.5],[1,0.5]];portConstraint=eastwest;labelBackgroundColor=none;" parent="report-class" vertex="1">
          <mxGeometry y="158" width="200" height="42" as="geometry" />
        </mxCell>
        <mxCell id="user-order-rel" value="" style="endArrow=none;html=1;rounded=0;exitX=0.991;exitY=0.565;exitDx=0;exitDy=0;entryX=0;entryY=0.5;entryDx=0;entryDy=0;strokeWidth=2;exitPerimeter=0;labelBackgroundColor=none;fontColor=default;" parent="1" source="user-attrs" target="order-class" edge="1">
          <mxGeometry width="50" height="50" relative="1" as="geometry">
            <mxPoint x="400" y="300" as="sourcePoint" />
            <mxPoint x="450" y="250" as="targetPoint" />
            <Array as="points">
              <mxPoint x="400" y="160" />
            </Array>
          </mxGeometry>
        </mxCell>
        <mxCell id="user-order-card1" value="1" style="text;html=1;align=center;verticalAlign=middle;resizable=0;points=[];autosize=1;strokeColor=none;fillColor=none;fontStyle=1;fontSize=14;labelBackgroundColor=none;" parent="1" vertex="1">
          <mxGeometry x="250" y="125" width="30" height="30" as="geometry" />
        </mxCell>
        <mxCell id="user-order-card2" value="*" style="text;html=1;align=center;verticalAlign=middle;resizable=0;points=[];autosize=1;strokeColor=none;fillColor=none;fontStyle=1;fontSize=14;labelBackgroundColor=none;" parent="1" vertex="1">
          <mxGeometry x="1000" y="160" width="30" height="30" as="geometry" />
        </mxCell>
        <mxCell id="user-order-label" value="assigns" style="text;html=1;align=center;verticalAlign=middle;resizable=0;points=[];autosize=1;strokeColor=none;fillColor=none;fontStyle=1;fontSize=12;labelBackgroundColor=none;" parent="1" vertex="1">
          <mxGeometry x="340" y="170" width="60" height="30" as="geometry" />
        </mxCell>
        <mxCell id="order-orderitem-rel" value="" style="endArrow=none;html=1;rounded=0;exitX=1;exitY=0.5;exitDx=0;exitDy=0;strokeWidth=2;entryX=0.943;entryY=0.99;entryDx=0;entryDy=0;entryPerimeter=0;labelBackgroundColor=none;fontColor=default;" parent="1" source="order-class" target="order-orderitem-card2" edge="1">
          <mxGeometry width="50" height="50" relative="1" as="geometry">
            <mxPoint x="400" y="300" as="sourcePoint" />
            <mxPoint x="880" y="320" as="targetPoint" />
            <Array as="points" />
          </mxGeometry>
        </mxCell>
        <mxCell id="order-orderitem-card1" value="1" style="text;html=1;align=center;verticalAlign=middle;resizable=0;points=[];autosize=1;strokeColor=none;fillColor=none;fontStyle=1;fontSize=14;labelBackgroundColor=none;" parent="1" vertex="1">
          <mxGeometry x="690" y="125" width="30" height="30" as="geometry" />
        </mxCell>
        <mxCell id="order-orderitem-card2" value="*" style="text;html=1;align=center;verticalAlign=middle;resizable=0;points=[];autosize=1;strokeColor=none;fillColor=none;fontStyle=1;fontSize=14;labelBackgroundColor=none;" parent="1" vertex="1">
          <mxGeometry x="770" y="130" width="30" height="30" as="geometry" />
        </mxCell>
        <mxCell id="order-orderitem-label" value="contains" style="text;html=1;align=center;verticalAlign=middle;resizable=0;points=[];autosize=1;strokeColor=none;fillColor=none;fontStyle=1;fontSize=12;labelBackgroundColor=none;" parent="1" vertex="1">
          <mxGeometry x="720" y="170" width="60" height="30" as="geometry" />
        </mxCell>
        <mxCell id="menu-orderitem-rel" value="" style="endArrow=none;html=1;rounded=0;exitX=0.5;exitY=0;exitDx=0;exitDy=0;strokeWidth=2;labelBackgroundColor=none;fontColor=default;" parent="1" source="menuitem-class" edge="1">
          <mxGeometry width="50" height="50" relative="1" as="geometry">
            <mxPoint x="400" y="300" as="sourcePoint" />
            <mxPoint x="1000" y="160" as="targetPoint" />
            <Array as="points">
              <mxPoint x="1050" y="160" />
            </Array>
          </mxGeometry>
        </mxCell>
        <mxCell id="menu-orderitem-card1" value="1" style="text;html=1;align=center;verticalAlign=middle;resizable=0;points=[];autosize=1;strokeColor=none;fillColor=none;fontStyle=1;fontSize=14;labelBackgroundColor=none;" parent="1" vertex="1">
          <mxGeometry x="1020" y="260" width="30" height="30" as="geometry" />
        </mxCell>
        <mxCell id="menu-orderitem-card2" value="*" style="text;html=1;align=center;verticalAlign=middle;resizable=0;points=[];autosize=1;strokeColor=none;fillColor=none;fontStyle=1;fontSize=14;labelBackgroundColor=none;" parent="1" vertex="1">
          <mxGeometry x="460" y="130" width="30" height="30" as="geometry" />
        </mxCell>
        <mxCell id="menu-orderitem-label" value="ordered as" style="text;html=1;align=center;verticalAlign=middle;resizable=0;points=[];autosize=1;strokeColor=none;fillColor=none;fontStyle=1;fontSize=12;labelBackgroundColor=none;" parent="1" vertex="1">
          <mxGeometry x="1070" y="200" width="70" height="30" as="geometry" />
        </mxCell>
        <mxCell id="order-bill-rel" value="" style="endArrow=none;html=1;rounded=0;exitX=0.5;exitY=1;exitDx=0;exitDy=0;entryX=0.5;entryY=0;entryDx=0;entryDy=0;strokeWidth=2;labelBackgroundColor=none;fontColor=default;" parent="1" source="order-class" target="bill-class" edge="1">
          <mxGeometry width="50" height="50" relative="1" as="geometry">
            <mxPoint x="400" y="300" as="sourcePoint" />
            <mxPoint x="450" y="250" as="targetPoint" />
          </mxGeometry>
        </mxCell>
        <mxCell id="order-bill-card1" value="1" style="text;html=1;align=center;verticalAlign=middle;resizable=0;points=[];autosize=1;strokeColor=none;fillColor=none;fontStyle=1;fontSize=14;labelBackgroundColor=none;" parent="1" vertex="1">
          <mxGeometry x="590" y="450" width="30" height="30" as="geometry" />
        </mxCell>
        <mxCell id="order-bill-card2" value="1" style="text;html=1;align=center;verticalAlign=middle;resizable=0;points=[];autosize=1;strokeColor=none;fillColor=none;fontStyle=1;fontSize=14;labelBackgroundColor=none;" parent="1" vertex="1">
          <mxGeometry x="590" y="290" width="30" height="30" as="geometry" />
        </mxCell>
        <mxCell id="order-bill-label" value="generates" style="text;html=1;align=center;verticalAlign=middle;resizable=0;points=[];autosize=1;strokeColor=none;fillColor=none;fontStyle=1;fontSize=12;labelBackgroundColor=none;" parent="1" vertex="1">
          <mxGeometry x="510" y="370" width="70" height="30" as="geometry" />
        </mxCell>
        <mxCell id="user-report-rel" value="" style="endArrow=none;html=1;rounded=0;exitX=0.5;exitY=1;exitDx=0;exitDy=0;entryX=0.5;entryY=0;entryDx=0;entryDy=0;strokeWidth=2;labelBackgroundColor=none;fontColor=default;" parent="1" source="user-class" target="report-class" edge="1">
          <mxGeometry width="50" height="50" relative="1" as="geometry">
            <mxPoint x="400" y="300" as="sourcePoint" />
            <mxPoint x="450" y="250" as="targetPoint" />
            <Array as="points">
              <mxPoint x="150" y="440" />
            </Array>
          </mxGeometry>
        </mxCell>
        <mxCell id="user-report-card1" value="1" style="text;html=1;align=center;verticalAlign=middle;resizable=0;points=[];autosize=1;strokeColor=none;fillColor=none;fontStyle=1;fontSize=14;labelBackgroundColor=none;" parent="1" vertex="1">
          <mxGeometry x="150" y="270" width="30" height="30" as="geometry" />
        </mxCell>
        <mxCell id="user-report-card2" value="*" style="text;html=1;align=center;verticalAlign=middle;resizable=0;points=[];autosize=1;strokeColor=none;fillColor=none;fontStyle=1;fontSize=14;labelBackgroundColor=none;" parent="1" vertex="1">
          <mxGeometry x="150" y="410" width="30" height="30" as="geometry" />
        </mxCell>
        <mxCell id="user-report-label" value="creates" style="text;html=1;align=center;verticalAlign=middle;resizable=0;points=[];autosize=1;strokeColor=none;fillColor=none;fontStyle=1;fontSize=12;rotation=0;labelBackgroundColor=none;" parent="1" vertex="1">
          <mxGeometry x="160" y="340" width="50" height="30" as="geometry" />
        </mxCell>
      </root>
    </mxGraphModel>
  </diagram>
</mxfile>
